{
  "id": "displacement-cs",
  "slug": "customer-service-automation",
  "title": "Customer Service Automation by 2028",
  "description": "Percentage of customer service interactions fully handled by AI without human intervention. Only data points where sources directly state an automation rate are plotted.",
  "category": "displacement",
  "unit": "% of interactions automated",
  "currentValue": 55,
  "timeHorizon": "By 2028",
  "history": [
    {
      "date": "2024-01-20",
      "value": 66,
      "confidenceLow": 55,
      "confidenceHigh": 75,
      "sourceIds": [
        "klarna-earnings-2024"
      ],
      "evidenceTier": 1
    },
    {
      "date": "2024-02-01",
      "value": 12,
      "confidenceLow": 8,
      "confidenceHigh": 18,
      "sourceIds": [
        "shopify-earnings-2024"
      ],
      "evidenceTier": 1
    },
    {
      "date": "2025-02-12",
      "value": 40,
      "confidenceLow": 30,
      "confidenceHigh": 50,
      "sourceIds": [
        "shopify-earnings-2024"
      ],
      "evidenceTier": 1
    },
    {
      "date": "2026-02-01",
      "value": 55,
      "confidenceLow": 45,
      "confidenceHigh": 65,
      "sourceIds": [
        "zendesk-ai-cs-2026"
      ],
      "evidenceTier": 3
    }
  ],
  "overlays": [
    {
      "date": "2024-09-01",
      "direction": "up",
      "sourceIds": [
        "huang-cs-2024"
      ],
      "evidenceTier": 1,
      "label": "NBER: AI boosts CS worker productivity 14%"
    },
    {
      "date": "2025-05-01",
      "direction": "up",
      "sourceIds": [
        "brynjolfsson-li-raymond-qje-2025"
      ],
      "evidenceTier": 1,
      "label": "QJE: 15% productivity gain, novices benefit most"
    },
    {
      "date": "2025-08-01",
      "direction": "down",
      "sourceIds": [
        "brynjolfsson-chandar-chen-cs-2025"
      ],
      "evidenceTier": 1,
      "label": "Stanford: 11% decline for early-career CS workers"
    },
    {
      "date": "2025-11-01",
      "direction": "down",
      "sourceIds": [
        "gartner-cs-2026-forecast"
      ],
      "evidenceTier": 2,
      "label": "Gartner: 20-30% of CS agents replaced by 2026"
    },
    {
      "date": "2025-10-01",
      "direction": "up",
      "sourceIds": [
        "bofa-erica-ai-2025"
      ],
      "evidenceTier": 1,
      "label": "BofA Erica: 2B interactions, 98% resolution rate"
    },
    {
      "date": "2025-06-01",
      "direction": "neutral",
      "sourceIds": [
        "klarna-reversal-2025"
      ],
      "evidenceTier": 1,
      "label": "Klarna reversed course, rehiring humans after 22% CSAT drop"
    },
    {
      "date": "2025-03-05",
      "direction": "up",
      "sourceIds": [
        "gartner-agentic-ai-cs-2025"
      ],
      "evidenceTier": 2,
      "label": "Gartner: agentic AI to resolve 80% of common CS issues by 2029"
    },
    {
      "date": "2025-05-27",
      "direction": "up",
      "sourceIds": [
        "cisco-agentic-cs-2025"
      ],
      "evidenceTier": 2,
      "label": "Cisco: 68% of CS interactions by agentic AI by 2028"
    },
    {
      "date": "2025-10-01",
      "direction": "up",
      "sourceIds": [
        "fang-ecommerce-chatbots-2025"
      ],
      "evidenceTier": 1,
      "label": "E-commerce field experiment: AI chatbots increased sales 16%"
    }
  ],
  "sources": [
    {
      "id": "gartner-cs-2023",
      "title": "Gartner Predicts Conversational AI Will Reduce Contact Center Agent Labor Costs by $80 Billion in 2026",
      "url": "https://www.gartner.com/en/newsroom/press-releases/2023-08-30-gartner-reveals-three-technologies-that-will-transform-customer-service-and-support-by-2028",
      "publisher": "Gartner",
      "evidenceTier": 2,
      "datePublished": "2023-08-30"
    },
    {
      "id": "forrester-cs-2023",
      "title": "The State Of Customer Service Automation",
      "url": "https://www.forrester.com/report/the-state-of-customer-service-automation/",
      "publisher": "Forrester",
      "evidenceTier": 2,
      "datePublished": "2023-08-15"
    },
    {
      "id": "klarna-earnings-2024",
      "title": "Klarna AI assistant handles two-thirds of customer service chats in first month",
      "url": "https://www.klarna.com/international/press/klarna-ai-assistant-handles-two-thirds-of-customer-service-chats-in-its-first-month/",
      "publisher": "Klarna",
      "evidenceTier": 1,
      "datePublished": "2024-02-27",
      "excerpt": "Klarna's AI assistant handled 2.3 million conversations, doing the equivalent work of 700 full-time agents."
    },
    {
      "id": "hbr-chatbots-2024",
      "title": "How AI is Transforming Customer Service",
      "url": "https://hbr.org/2023/03/generative-ai-will-enhance-not-erase-customer-service-jobs",
      "publisher": "Harvard Business Review",
      "evidenceTier": 3,
      "datePublished": "2024-05-10"
    },
    {
      "id": "huang-cs-2024",
      "title": "Generative AI and Customer Service: Evidence from Customer Support Interactions",
      "url": "https://www.nber.org/papers/w31161",
      "publisher": "NBER (Brynjolfsson, Li, Raymond)",
      "evidenceTier": 1,
      "datePublished": "2024-09-01",
      "excerpt": "AI assistance increased worker productivity by 14% on average, with greatest gains for novice and low-skilled workers."
    },
    {
      "id": "gartner-cs-2025",
      "title": "Gartner: By 2027, 25% of organizations will use chatbots as primary customer service channel",
      "url": "https://www.gartner.com/en/newsroom/press-releases/2022-07-27-gartner-predicts-chatbots-will-become-a-primary-customer-service-channel-within-five-years",
      "publisher": "Gartner",
      "evidenceTier": 2,
      "datePublished": "2025-01-15"
    },
    {
      "id": "tdoc-10k-2024",
      "title": "Teleperformance: 2024 Annual Results",
      "url": "https://www.businesswire.com/news/home/20250227092643/en/Teleperformance-2024-Annual-Results",
      "publisher": "Teleperformance SE (via BusinessWire)",
      "evidenceTier": 2,
      "datePublished": "2025-02-27",
      "excerpt": "Teleperformance reported full-year 2024 revenue of EUR 10,280 million. Plans to invest up to EUR 100 million in AI-focused partnerships during 2025. Over 200 new AI projects launched in 2024."
    },
    {
      "id": "indeed-cs-postings-2025",
      "title": "Customer Service Job Postings Decline 18% YoY",
      "url": "https://www.hiringlab.org/2024/12/10/indeed-2025-us-jobs-and-hiring-trends-report/",
      "publisher": "Indeed Hiring Lab",
      "evidenceTier": 2,
      "datePublished": "2025-01-15",
      "excerpt": "Customer service representative postings declined 18% year-over-year. Remaining postings increasingly require technical skills and AI tool familiarity."
    },
    {
      "id": "shopify-earnings-2024",
      "title": "Shopify Q4 2024 Earnings — AI Customer Support Metrics",
      "url": "https://investors.shopify.com/financial-reports",
      "publisher": "Shopify (Earnings Call)",
      "evidenceTier": 1,
      "datePublished": "2025-02-12",
      "excerpt": "Shopify reported its AI assistant Sidekick now resolves 40% of merchant support queries without human intervention, up from 12% one year prior."
    },
    {
      "id": "gartner-cs-2026-forecast",
      "title": "Gartner Forecasts 20-30% of CS Agents Replaced by GenAI by 2026",
      "url": "https://www.gartner.com/en/newsroom/press-releases/2023-08-03-customer-service-and-support-leaders-should-assess-generative-ai-technology-options-to-enhance-their-organizations-function",
      "publisher": "Gartner",
      "evidenceTier": 2,
      "datePublished": "2025-10-15",
      "excerpt": "Gartner projects 20-30% of customer service agents will be replaced by generative AI by end of 2026. AI adoption in CS jumped from 46% to 61% in one year."
    },
    {
      "id": "zendesk-ai-cs-2026",
      "title": "Zendesk AI Customer Service Statistics 2026",
      "url": "https://www.zendesk.com/blog/ai-customer-service-statistics/",
      "publisher": "Zendesk",
      "evidenceTier": 3,
      "datePublished": "2026-01-15",
      "excerpt": "95% of customer interactions projected to be AI-powered by 2028. Current AI resolution rates at leading companies exceed 55% without human escalation."
    },
    {
      "id": "brynjolfsson-li-raymond-qje-2025",
      "title": "Generative AI at Work",
      "url": "https://academic.oup.com/qje/article/140/2/889/7990658",
      "publisher": "QJE (Brynjolfsson, Li, Raymond)",
      "evidenceTier": 1,
      "datePublished": "2025-05-01",
      "excerpt": "AI assistance increases customer service worker productivity by 15% on average. Less experienced workers improve most; AI disseminates best practices from top performers."
    },
    {
      "id": "brynjolfsson-chandar-chen-cs-2025",
      "title": "Canaries in the Coal Mine? Six Facts about the Recent Employment Effects of AI",
      "url": "https://digitaleconomy.stanford.edu/wp-content/uploads/2025/08/Canaries_BrynjolfssonChandarChen.pdf",
      "publisher": "Stanford Digital Economy Lab",
      "evidenceTier": 1,
      "datePublished": "2025-08-01",
      "excerpt": "~11% decline for early-career customer service workers; declines concentrated in roles where AI automates rather than augments tasks."
    },
    {
      "id": "bofa-erica-ai-2025",
      "title": "Bank of America: Erica AI Assistant Surpasses 2 Billion Interactions",
      "url": "https://newsroom.bankofamerica.com/content/newsroom/press-releases/2025/10/bank-of-america-s-erica-surpasses-2-billion-interactions.html",
      "publisher": "Bank of America",
      "evidenceTier": 1,
      "datePublished": "2025-10-01",
      "excerpt": "BofA's Erica AI assistant surpassed 2 billion client interactions with a 98% resolution rate. Now handles 56% of all customer inquiries without human escalation."
    },
    {
      "id": "klarna-reversal-2025",
      "title": "Klarna Reverses Course on AI-Only Customer Service, Rehires Human Agents",
      "url": "https://www.entrepreneur.com/business-news/klarna-ceo-reverses-course-by-hiring-more-humans-not-ai/491396",
      "publisher": "Entrepreneur / Klarna",
      "evidenceTier": 1,
      "datePublished": "2025-06-01",
      "excerpt": "Klarna reversed its AI-only CS strategy after customer satisfaction dropped 22%. CEO Siemiatkowski: 'we went too far.' Now operates hybrid model with AI handling ~66% but humans for complex cases."
    },
    {
      "id": "gartner-agentic-ai-cs-2025",
      "title": "Gartner Predicts Agentic AI Will Resolve 80% of Common Customer Service Issues by 2029",
      "url": "https://www.gartner.com/en/newsroom/press-releases/2025-03-05-gartner-predicts-agentic-ai-will-autonomously-resolve-80-percent-of-common-customer-service-issues-without-human-intervention-by-20290",
      "publisher": "Gartner",
      "evidenceTier": 2,
      "datePublished": "2025-03-05",
      "excerpt": "Agentic AI will autonomously resolve 80% of common customer service issues by 2029. Currently only 1.6% of interactions are fully automated end-to-end."
    },
    {
      "id": "cisco-agentic-cs-2025",
      "title": "The Race to an Agentic Future: Customer Service Interactions",
      "url": "https://newsroom.cisco.com/c/r/newsroom/en/us/a/y2025/m05/agentic-ai-poised-to-handle-68-of-customer-service-and-support-interactions-by-2028.html",
      "publisher": "Cisco",
      "evidenceTier": 2,
      "datePublished": "2025-05-27",
      "excerpt": "Survey of 7,950 decision-makers: 68% of all CS interactions expected to be handled by agentic AI by 2028. 56% expected within 12 months."
    },
    {
      "id": "fang-ecommerce-chatbots-2025",
      "title": "The Impact of AI on E-Commerce: Field Experiments on Customer Service and Product Descriptions",
      "url": "https://arxiv.org/abs/2510.12049",
      "publisher": "arXiv (Fang, Yuan, Zheng, Donati, Sarvary)",
      "evidenceTier": 1,
      "datePublished": "2025-10-01",
      "excerpt": "AI chatbots for customer service increased sales by 16%; AI-generated product descriptions increased sales by 2.05% in field experiments."
    }
  ]
}
